flaskr/__init__.py
flaskr/static/chartcore.min.js
flaskr/static/dash.css
flaskr/static/piechart.min.js
flaskr/templates/stats.html
CloudRepoAnalytics-2.0.0.dist-info/LICENSE
CloudRepoAnalytics-2.0.0.dist-info/METADATA
CloudRepoAnalytics-2.0.0.dist-info/WHEEL
CloudRepoAnalytics-2.0.0.dist-info/top_level.txt
CloudRepoAnalytics-2.0.0.dist-info/RECORD
